responseutils/__init__.py
responseutils/general.py
drf_response_utils-0.0.2.dist-info/LICENSE
drf_response_utils-0.0.2.dist-info/METADATA
drf_response_utils-0.0.2.dist-info/WHEEL
drf_response_utils-0.0.2.dist-info/top_level.txt
drf_response_utils-0.0.2.dist-info/RECORD
